{"id":"lifesmart-ls-core-202","brand":"LifeSmart","sku":"LS-CORE-202","title":"LifeSmart Cololight Connector","category":"Smart Home / Cololight","description":"An accessory that connects two cololight blocks and conveys control signal and power","availability":"Catalogue information under review / availability under review","unitPerCarton":null,"warranty":"To be confirmed","displayPriceUsd":1,"fullCartonUnitPriceUsd":1,"imageUrl":null,"documents":[],"enrichmentStatus":"lifesmart_source_xlsx","cartonAvailable":false}