{"id":"lifesmart-ls204wh","brand":"LifeSmart","sku":"LS204WH","title":"LifeSmart DEFED Indoor Siren LS204WH","category":"Smart Home / Siren","description":"Indoor Siren is a warning device in home security system with LED indicator and temperature sensor, providing sounds >80dB. As there is an intruder, the equipment will be triggered to drive him/her away.\nCertificate: 54.99 | Adapter: Battery | Packaging: English | EAN: 6932046203029 | HS code: 8531100000 | Package size: 8.8*4.3*8.8 | Weight: 0.154 kg","availability":"Catalogue information under review / availability under review","unitPerCarton":50,"warranty":"To be confirmed","displayPriceUsd":27,"fullCartonUnitPriceUsd":26,"imageUrl":null,"documents":[],"enrichmentStatus":"lifesmart_source_xlsx","cartonAvailable":true}