{
  "id": "ubiquiti-rad-rd3",
  "brand": "Ubiquiti",
  "sku": "RAD-RD3",
  "title": "Ubiquiti Radome for 3´ RocketDish 34dBi",
  "category": "Ubiquiti / Wireless / Antennas / Radom shields",
  "description": "A protective radome is available as an optional accessory for the RD-5G34 and AF-5G34-S45 provides the following advantages: Reduces wind load Protects antenna surfaces from natureâs harshest elements Conceals antenna feed equipment from public view Reduces wind load Protects antenna surfaces from natureâs harshest elements Conceals antenna feed equipment from public view",
  "availability": "In Stock 3 pcs.",
  "unitPerCarton": 5,
  "warranty": "24 months",
  "displayPriceUsd": 101,
  "fullCartonUnitPriceUsd": 97.47,
  "imageUrl": "assets/catalog-data/public-images/ubiquiti-rad-rd3-6acac17d59.jpg",
  "documents": [],
  "enrichmentStatus": "ok",
  "cartonAvailable": true,
  "stockQtyVisible": 3,
  "discompProductUrl": "https://www.discomp.cz/ubiquiti-radome-for-3-rocketdish-34dbi_d28492.html",
  "discompCategoryUrl": "https://www.discomp.cz/ubiquiti-wireless-antennas-radom-shields_c15888551.html",
  "discompSourcePath": [
    "Ubiquiti",
    "Wireless",
    "Antennas",
    "Radom shields"
  ]
}
