{"id":"mikrotik-rbftc11","brand":"MikroTik","sku":"RBFTC11","title":"MikroTik RBFTC11, Fiber to Copper Converter","category":"Wireless / MikroTik / RouterBOARD","description":"The FTC is a simple Fiber to Copper converter without management. Unlike many other media converters available on market, it has outdoor waterproof case with lock screw, it's mounting bracket can be attached and locked with a screw from inside the case. Unit has 12-57V PoE with 802.3af/at support. Comes with PoE injector and power supply. Works only with Gigabit SFP connections Device Power adapter 24V/0.2A Gigabit PoE injector wAP mount + screws","availability":"In stock","unitPerCarton":20,"warranty":"24 months","displayPriceUsd":36,"fullCartonUnitPriceUsd":34.74,"imageUrl":"assets/catalog-data/public-images/mikrotik-rbftc11-22ce6af430.jpg","documents":[],"enrichmentStatus":"ok","cartonAvailable":true,"specsSearch":"Connectors and Interfaces Optical Connectors (1) SFP LAN speed (1) 10/100/1000Mbps Gigabit LAN Yes Optical interfaces (1) 1000Mbps Power Power over Ethernet 802.3af, 802.3at, 12 .. 57V DC Power type PoE PoE type PoE-In (only)"}