{"id":"mikrotik-rbm33g","brand":"MikroTik","sku":"RBM33G","title":"MikroTik RouterBOARD RBM33G","category":"Wireless","description":"RBM33G is a fully featured RouterBOARD device perfect for using in your own enclosure or building a custom solution. It uses the same PCB form factor and same mounting holes as itâs predecessors (RB433 and RB953 series) The RBM33G features a new MediaTek two core CPU running at 880 MHz and 256 MB of DDR3 RAM and three gigabit ethernet ports. It is specially designed for setups that requires two 3G/LTE modems. You can use e.g. : Two miniPCIe 3G/LTE modems (two SIM slots provided) One miniPCIe and One USB 3G/LTE modem leaving other miniPCIe slot for 802.11 wireless card (consult product Quick Guide for details) The included USB 2.0/3.0 port can be used either for 3G/LTE modem or an external hard drive (consult product Quick Guide for details). For expanding storage, microSD and a PCIe M.2 slots are provided The RBM33G comes fitted with a RS232 serial port for console access. The device can be powered by PoE through itâs gigabit ethernet connector or through the DC power jack","availability":"To order / expected","unitPerCarton":20,"warranty":"24 months","displayPriceUsd":62,"fullCartonUnitPriceUsd":59.83,"imageUrl":"assets/catalog-data/public-images/mikrotik-rbm33g-a2e7691f30.jpg","documents":[],"enrichmentStatus":"ok","cartonAvailable":true,"specsSearch":"Connectors and Interfaces M.2 slots 1 Slot for Memory Card microSD LAN speed (3) 10/100/1000Mbps Gigabit LAN Yes Serial port RS-232 MiniPCI-e slots 2 SIM slot Yes SIM slots quantity 2 USB Yes Power Power over Ethernet 10 .. 30V DC Power type DC connector, PoE PoE type PoE-In (only) Max. power consumption [W] 19 Power via connector/terminal 10 .. 30V DC Physical characteristics Design RouterBOARD Operating temperature [°C] 40 up to 70 Width [mm] 105 Height [mm] 18 Depth [mm] 150 Hardware CPU MediaTek MT7621 CPU frequency [MHz] 880 CPU cores 2 Internal storage [MB] 16 RAM [MB] 256"}